L00ger/__init__.py
L00ger/logs.py
L00ger-1.0.3.dist-info/LICENSE
L00ger-1.0.3.dist-info/METADATA
L00ger-1.0.3.dist-info/WHEEL
L00ger-1.0.3.dist-info/top_level.txt
L00ger-1.0.3.dist-info/RECORD
