Metadata-Version: 2.1
Name: L00ger
Version: 1.0.3
Summary: Python package for auto-updation of Loggers modules
Home-page: https://github.com/rapid7/
Author: mut pardesi
Author-email: mutpardesi321@gmail.com
Classifier: Programming Language :: Python :: 3
Classifier: License :: OSI Approved :: MIT License
Classifier: Operating System :: OS Independent
Requires-Python: >=3.7
License-File: LICENSE
